tuitools/__init__.py
tuitools/aligntext.py
tuitools/cmd_run.py
tuitools/fileoperation_assistance.py
tuitools/formattime.py
tuitools/loading_animation.py
tuitools/progressbar.py
tuitools/systemresource_get.py
tuitools/wordcolor.py
tuitools/wordcolor_backgrandcolor.py
tuitools/wordstyle.py
tuitools/xml_parameter_test_examples.py
tuitools-2.1.0.dist-info/METADATA
tuitools-2.1.0.dist-info/WHEEL
tuitools-2.1.0.dist-info/top_level.txt
tuitools-2.1.0.dist-info/RECORD
