Metadata-Version: 2.1
Name: tuitools
Version: 2.1.0
Author: Paddy Hong
Author-email: 1707262291@qq.com
